td_pyspark/__init__.py
td_pyspark/td_pyspark.py
td_pyspark/version.py
td_pyspark/jars/td-spark-assembly.jar
td_pyspark/tests/__init__.py
td_pyspark/tests/test_pyspark.py
td_pyspark/tests/test_pyspark_without_td_spark.py
td_pyspark_ea-20.12.0.dist-info/METADATA
td_pyspark_ea-20.12.0.dist-info/WHEEL
td_pyspark_ea-20.12.0.dist-info/top_level.txt
td_pyspark_ea-20.12.0.dist-info/RECORD
