Metadata-Version: 2.1
Name: td-pyspark-ea
Version: 20.12.0
Summary: Treasure Data extension for pyspark
Home-page: https://tddocs.atlassian.net/wiki/spaces/PD/pages/542933139/Data+Science+and+SQL+Tools
Author: Treasure Data
Author-email: dev+pypi@treasure-data.com
License: Apache 2
Keywords: Spark PySpark TreasureData
Platform: UNKNOWN
Classifier: Programming Language :: Python :: 3
Classifier: License :: OSI Approved :: Apache Software License
Classifier: Operating System :: OS Independent
Provides-Extra: docs
Requires-Dist: sphinx (>=2.2.0) ; extra == 'docs'
Requires-Dist: sphinx-rtd-theme (>=0.4.3) ; extra == 'docs'
Requires-Dist: recommonmark ; extra == 'docs'
Provides-Extra: spark
Requires-Dist: pyspark (>=3.0.1) ; extra == 'spark'
